luga/__init__.py
luga/artifacts.py
luga/luga.py
luga-0.2.7.dist-info/METADATA
luga-0.2.7.dist-info/LICENSE
luga-0.2.7.dist-info/WHEEL
luga-0.2.7.dist-info/RECORD
