Metadata-Version: 2.1
Name: luga
Version: 0.2.7
Summary: Sensing the language of the text using Machine Learning
Home-page: https://github.com/Proteusiq/luga
Author: Prayson W. Daniel
Author-email: praysonwilfred@gmail.com
Requires-Python: >=3.7.1,<4.0.0
Classifier: Programming Language :: Python :: 3
Classifier: Programming Language :: Python :: 3.8
Classifier: Programming Language :: Python :: 3.9
Classifier: Programming Language :: Python :: 3.10
Classifier: Programming Language :: Python :: 3.11
Requires-Dist: fasttext-wheel (>=0.9.2,<0.10.0)
Requires-Dist: gdown (>=4.4.0,<5.0.0)
Requires-Dist: nptyping (>=1.4.4,<2.0.0)
Requires-Dist: numpy (>=1.20,<2.0)
Project-URL: Repository, https://github.com/Proteusiq/luga
